[
  {
    "name": "Uchimata",
    "id": "1",
    "url": "https://youtu.be/hNV9Oh2B_Kc"
  },
  {
    "name": "Harai goshi",
    "id": "2",
    "url": "https://youtu.be/hNV9Oh2B_Kc"
  },
  {
    "name": "Seoi nage",
    "id": "3",
    "url": "https://youtu.be/hNV9Oh2B_Kc"
  },
  {
    "name": "Ko uchi gari",
    "id": "4",
    "url": "https://youtu.be/hNV9Oh2B_Kc"
  },
  {
    "name": "O soto gari",
    "id": "5",
    "url": "https://youtu.be/hNV9Oh2B_Kc"
  },
  {
    "name": "Kubinage",
    "id": "6",
    "url": "https://youtu.be/hNV9Oh2B_Kc"
  },
  {
    "name": "Yoko tomoe nage",
    "id": "7",
    "url": "https://youtu.be/hNV9Oh2B_Kc"
  },
  {
    "name": "Kata guruma",
    "id": "8",
    "url": "https://youtu.be/hNV9Oh2B_Kc"
  }
]
